mahiruapi/__init__.py
mahiruapi/notifier.py
mahirulauncher_api-0.1.2.dist-info/LICENSE
mahirulauncher_api-0.1.2.dist-info/METADATA
mahirulauncher_api-0.1.2.dist-info/WHEEL
mahirulauncher_api-0.1.2.dist-info/top_level.txt
mahirulauncher_api-0.1.2.dist-info/RECORD
