Metadata-Version: 2.1
Name: mahirulauncher-api
Version: 0.1.2
Summary: MahiruLauncher API Package for Python
Home-page: https://github.com/JeffersonQin/MahiruLauncher.Api.Python
Author: JeffersonQin
Author-email: 1247006353@qq.com
License: MIT License
Keywords: launcher,api,scheduler
Platform: UNKNOWN
License-File: LICENSE
Requires-Dist: requests
